goldhandtest/__init__.py
goldhandtest/main.py
goldhandtest-1.0.dist-info/METADATA
goldhandtest-1.0.dist-info/WHEEL
goldhandtest-1.0.dist-info/top_level.txt
goldhandtest-1.0.dist-info/RECORD
