Metadata-Version: 2.1
Name: goldhandtest
Version: 1.0
Summary: A description of your package
Home-page: UNKNOWN
Author: Mihaly
Author-email: ormraat.pte@gmail.com
License: MIT
Platform: UNKNOWN
